[
    {
        "id": 2,
        "nombre": "Afnan 9pm ",
        "imagen": "afnan-9pm",
        "casa": "Afnan",
        "precio": "299.000 COP",
        "disponibilidad": "Solo original",
        "descripcion": "Perfume Afnan 9pm  de la casa Afnan, conocido por su elegancia y sofisticación.",
        "aromas": "Aroma variado"
    },
    {
        "id": 3,
        "nombre": "AHLI Alpha",
        "imagen": "ahli-alpha",
        "casa": "AHLI",
        "precio": "450.000 COP",
        "disponibilidad": "Solo original",
        "descripcion": "Perfume AHLI Alpha de la casa AHLI, conocido por su elegancia y sofisticación.",
        "aromas": "Aroma variado"
    },
    {
        "id": 4,
        "nombre": "AHLI Apus",
        "imagen": "ahli-apus",
        "casa": "AHLI",
        "precio": "450.000 COP",
        "disponibilidad": "Solo original",
        "descripcion": "Perfume AHLI Apus de la casa AHLI, conocido por su elegancia y sofisticación.",
        "aromas": "Aroma variado"
    },
    {
        "id": 5,
        "nombre": "AHLI Ara",
        "imagen": "ahli-ara",
        "casa": "AHLI",
        "precio": "450.000 COP",
        "disponibilidad": "Solo original",
        "descripcion": "Perfume AHLI Ara de la casa AHLI, conocido por su elegancia y sofisticación.",
        "aromas": "Aroma variado"
    },
    {
        "id": 6,
        "nombre": "AHLI Auriga",
        "imagen": "ahli-auriga",
        "casa": "AHLI",
        "precio": "450.000 COP",
        "disponibilidad": "Solo original",
        "descripcion": "Perfume AHLI Auriga de la casa AHLI, conocido por su elegancia y sofisticación.",
        "aromas": "Aroma variado"
    },
    {
        "id": 7,
        "nombre": "AHLI Beta",
        "imagen": "ahli-beta",
        "casa": "AHLI",
        "precio": "450.000 COP",
        "disponibilidad": "Solo original",
        "descripcion": "Perfume AHLI Beta de la casa AHLI, conocido por su elegancia y sofisticación.",
        "aromas": "Aroma variado"
    },
    {
        "id": 8,
        "nombre": "AHLI Canes",
        "imagen": "ahli-canes",
        "casa": "AHLI",
        "precio": "475.000 COP",
        "disponibilidad": "Solo original",
        "descripcion": "Perfume AHLI Canes de la casa AHLI, conocido por su elegancia y sofisticación.",
        "aromas": "Aroma variado"
    },
    {
        "id": 9,
        "nombre": "AHLI Corvus",
        "imagen": "ahli-corvus",
        "casa": "AHLI",
        "precio": "490.000 COP",
        "disponibilidad": "Solo original",
        "descripcion": "Perfume AHLI Corvus de la casa AHLI, conocido por su elegancia y sofisticación.",
        "aromas": "Aroma variado"
    },
    {
        "id": 10,
        "nombre": "AHLI Gemini",
        "imagen": "ahli-gemini",
        "casa": "AHLI",
        "precio": "450.000 COP",
        "disponibilidad": "Solo original",
        "descripcion": "Perfume AHLI Gemini de la casa AHLI, conocido por su elegancia y sofisticación.",
        "aromas": "Aroma variado"
    },
    {
        "id": 11,
        "nombre": "AHLI Karpos",
        "imagen": "ahli-karpos",
        "casa": "AHLI",
        "precio": "499.000 COP",
        "disponibilidad": "Solo original",
        "descripcion": "Perfume AHLI Karpos de la casa AHLI, conocido por su elegancia y sofisticación.",
        "aromas": "Aroma variado"
    },
    {
        "id": 12,
        "nombre": "AHLI Lyra",
        "imagen": "ahli-lyra",
        "casa": "AHLI",
        "precio": "450.000 COP",
        "disponibilidad": "Solo original",
        "descripcion": "Perfume AHLI Lyra de la casa AHLI, conocido por su elegancia y sofisticación.",
        "aromas": "Aroma variado"
    },
    {
        "id": 13,
        "nombre": "AHLI Naos",
        "imagen": "ahli-naos",
        "casa": "AHLI",
        "precio": "450.000 COP",
        "disponibilidad": "Solo original",
        "descripcion": "Perfume AHLI Naos de la casa AHLI, conocido por su elegancia y sofisticación.",
        "aromas": "Aroma variado"
    },
    {
        "id": 14,
        "nombre": "AHLI Octans",
        "imagen": "ahli-octans",
        "casa": "AHLI",
        "precio": "490.000 COP",
        "disponibilidad": "Solo original",
        "descripcion": "Perfume AHLI Octans de la casa AHLI, conocido por su elegancia y sofisticación.",
        "aromas": "Aroma variado"
    },
    {
        "id": 15,
        "nombre": "AHLI Orion",
        "imagen": "ahli-orion",
        "casa": "AHLI",
        "precio": "450.000 COP",
        "disponibilidad": "Solo original",
        "descripcion": "Perfume AHLI Orion de la casa AHLI, conocido por su elegancia y sofisticación.",
        "aromas": "Aroma variado"
    },
    {
        "id": 16,
        "nombre": "AHLI Overdose",
        "imagen": "ahli-overdose",
        "casa": "AHLI",
        "precio": "475.000 COP",
        "disponibilidad": "Solo original",
        "descripcion": "Perfume AHLI Overdose de la casa AHLI, conocido por su elegancia y sofisticación.",
        "aromas": "Aroma variado"
    },
    {
        "id": 17,
        "nombre": "AHLI Taurus",
        "imagen": "ahli-taurus",
        "casa": "AHLI",
        "precio": "450.000 COP",
        "disponibilidad": "Solo original",
        "descripcion": "Perfume AHLI Taurus de la casa AHLI, conocido por su elegancia y sofisticación.",
        "aromas": "Aroma variado"
    },
    {
        "id": 18,
        "nombre": "AHLI Vega",
        "imagen": "ahli-vega",
        "casa": "AHLI",
        "precio": "490.000 COP",
        "disponibilidad": "Solo original",
        "descripcion": "Perfume AHLI Vega de la casa AHLI, conocido por su elegancia y sofisticación.",
        "aromas": "Aroma variado"
    },
    {
        "id": 19,
        "nombre": "AHLI Virgo",
        "imagen": "ahli-virgo",
        "casa": "AHLI",
        "precio": "450.000 COP",
        "disponibilidad": "Solo original",
        "descripcion": "Perfume AHLI Virgo de la casa AHLI, conocido por su elegancia y sofisticación.",
        "aromas": "Aroma variado"
    },
    {
        "id": 20,
        "nombre": "Al Haramain Amber Oud Gold Edition 120 ml",
        "imagen": "al-haramain-amber-oud-gold-edition-120-ml",
        "casa": "Al Haramain",
        "precio": "425.000 COP",
        "disponibilidad": "Solo original",
        "descripcion": "Perfume Al Haramain Amber Oud Gold Edition 120 ml de la casa Al Haramain, conocido por su elegancia y sofisticación.",
        "aromas": "Amaderado"
    },
    {
        "id": 21,
        "nombre": "Al Haramain Amber Oud Gold Edition 60 ml",
        "imagen": "al-haramain-amber-oud-gold-edition-60-ml",
        "casa": "Al Haramain",
        "precio": "299.000 COP",
        "disponibilidad": "Solo original",
        "descripcion": "Perfume Al Haramain Amber Oud Gold Edition 60 ml de la casa Al Haramain, conocido por su elegancia y sofisticación.",
        "aromas": "Amaderado"
    },
    {
        "id": 22,
        "nombre": "Al Haramain L´Aventure",
        "imagen": "al-haramain-l´aventure",
        "casa": "Al Haramain",
        "precio": "280.000 COP",
        "disponibilidad": "Solo original",
        "descripcion": "Perfume Al Haramain L´Aventure de la casa Al Haramain, conocido por su elegancia y sofisticación.",
        "aromas": "Aroma variado"
    },
    {
        "id": 23,
        "nombre": "Al Haramain L´Aventure Blanche",
        "imagen": "al-haramain-l´aventure-blanche",
        "casa": "Al Haramain",
        "precio": "280.000 COP",
        "disponibilidad": "Solo original",
        "descripcion": "Perfume Al Haramain L´Aventure Blanche de la casa Al Haramain, conocido por su elegancia y sofisticación.",
        "aromas": "Aroma variado"
    },
    {
        "id": 24,
        "nombre": "Al Haramain L´Aventure Femme",
        "imagen": "al-haramain-l´aventure-femme",
        "casa": "Al Haramain",
        "precio": "280.000 COP",
        "disponibilidad": "Solo original",
        "descripcion": "Perfume Al Haramain L´Aventure Femme de la casa Al Haramain, conocido por su elegancia y sofisticación.",
        "aromas": "Aroma variado"
    },
    {
        "id": 25,
        "nombre": "Ariana Grande Cloud",
        "imagen": "ariana-grande-cloud",
        "casa": "Ariana Grande",
        "precio": "399.000 COP",
        "disponibilidad": "Solo original",
        "descripcion": "Perfume Ariana Grande Cloud de la casa Ariana Grande, conocido por su elegancia y sofisticación.",
        "aromas": "Amaderado"
    },
    {
        "id": 26,
        "nombre": "Ariana Grande Sweet Like Candy",
        "imagen": "ariana-grande-sweet-like-candy",
        "casa": "Ariana Grande",
        "precio": "320.000 COP",
        "disponibilidad": "Solo original",
        "descripcion": "Perfume Ariana Grande Sweet Like Candy de la casa Ariana Grande, conocido por su elegancia y sofisticación.",
        "aromas": "Dulce"
    },
    {
        "id": 27,
        "nombre": "Baroque Rouge EDP",
        "imagen": "baroque-rouge-edp",
        "casa": "Baroque",
        "precio": "265.000 COP",
        "disponibilidad": "Solo original",
        "descripcion": "Perfume Baroque Rouge EDP de la casa Baroque, conocido por su elegancia y sofisticación.",
        "aromas": "Aroma variado"
    },
    {
        "id": 28,
        "nombre": "Baroque Rouge Extrait",
        "imagen": "baroque-rouge-extrait",
        "casa": "Baroque",
        "precio": "365.000 COP",
        "disponibilidad": "Solo original",
        "descripcion": "Perfume Baroque Rouge Extrait de la casa Baroque, conocido por su elegancia y sofisticación.",
        "aromas": "Aroma variado"
    },
    {
        "id": 29,
        "nombre": "Bharara Don",
        "imagen": "bharara-don",
        "casa": "Bharara",
        "precio": "390.000 COP",
        "disponibilidad": "Solo original",
        "descripcion": "Perfume Bharara Don de la casa Bharara, conocido por su elegancia y sofisticación.",
        "aromas": "Aroma variado"
    },
    {
        "id": 30,
        "nombre": "Bharara Double Blue",
        "imagen": "bharara-double-blue",
        "casa": "Bharara",
        "precio": "390.000 COP",
        "disponibilidad": "Solo original",
        "descripcion": "Perfume Bharara Double Blue de la casa Bharara, conocido por su elegancia y sofisticación.",
        "aromas": "Aroma variado"
    },
    {
        "id": 31,
        "nombre": "Bharara King",
        "imagen": "bharara-king",
        "casa": "Bharara",
        "precio": "390.000 COP",
        "disponibilidad": "Solo original",
        "descripcion": "Perfume Bharara King de la casa Bharara, conocido por su elegancia y sofisticación.",
        "aromas": "Aroma variado"
    },
    {
        "id": 32,
        "nombre": "Bharara King Parfum",
        "imagen": "bharara-king-parfum",
        "casa": "Bharara",
        "precio": "490.000 COP",
        "disponibilidad": "Solo original",
        "descripcion": "Perfume Bharara King Parfum de la casa Bharara, conocido por su elegancia y sofisticación.",
        "aromas": "Aroma variado"
    },
    {
        "id": 33,
        "nombre": "Bharara Niche",
        "imagen": "bharara-niche",
        "casa": "Bharara",
        "precio": "390.000 COP",
        "disponibilidad": "Solo original",
        "descripcion": "Perfume Bharara Niche de la casa Bharara, conocido por su elegancia y sofisticación.",
        "aromas": "Aroma variado"
    },
    {
        "id": 34,
        "nombre": "Bharara Niche Femme",
        "imagen": "bharara-niche-femme",
        "casa": "Bharara",
        "precio": "390.000 COP",
        "disponibilidad": "Solo original",
        "descripcion": "Perfume Bharara Niche Femme de la casa Bharara, conocido por su elegancia y sofisticación.",
        "aromas": "Aroma variado"
    },
    {
        "id": 35,
        "nombre": "Bharara Viking Beirut",
        "imagen": "bharara-viking-beirut",
        "casa": "Bharara",
        "precio": "510.000 COP",
        "disponibilidad": "Solo original",
        "descripcion": "Perfume Bharara Viking Beirut de la casa Bharara, conocido por su elegancia y sofisticación.",
        "aromas": "Aroma variado"
    },
    {
        "id": 36,
        "nombre": "Bharara Viking Cairo",
        "imagen": "bharara-viking-cairo",
        "casa": "Bharara",
        "precio": "510.000 COP",
        "disponibilidad": "Solo original",
        "descripcion": "Perfume Bharara Viking Cairo de la casa Bharara, conocido por su elegancia y sofisticación.",
        "aromas": "Aroma variado"
    },
    {
        "id": 37,
        "nombre": "Bharara Viking Dubai",
        "imagen": "bharara-viking-dubai",
        "casa": "Bharara",
        "precio": "510.000 COP",
        "disponibilidad": "Solo original",
        "descripcion": "Perfume Bharara Viking Dubai de la casa Bharara, conocido por su elegancia y sofisticación.",
        "aromas": "Aroma variado"
    },
    {
        "id": 38,
        "nombre": "Bharara Viking Rio",
        "imagen": "bharara-viking-rio",
        "casa": "Bharara",
        "precio": "510.000 COP",
        "disponibilidad": "Solo original",
        "descripcion": "Perfume Bharara Viking Rio de la casa Bharara, conocido por su elegancia y sofisticación.",
        "aromas": "Aroma variado"
    },
    {
        "id": 39,
        "nombre": "Blackoud Amber Black",
        "imagen": "blackoud-amber-black",
        "casa": "Blackoud",
        "precio": "375.000 COP",
        "disponibilidad": "Solo original",
        "descripcion": "Perfume Blackoud Amber Black de la casa Blackoud, conocido por su elegancia y sofisticación.",
        "aromas": "Amaderado"
    },
    {
        "id": 40,
        "nombre": "Blackoud By Drew",
        "imagen": "blackoud-by-drew",
        "casa": "Blackoud",
        "precio": "375.000 COP",
        "disponibilidad": "Solo original",
        "descripcion": "Perfume Blackoud By Drew de la casa Blackoud, conocido por su elegancia y sofisticación.",
        "aromas": "Amaderado"
    },
    {
        "id": 41,
        "nombre": "Blackoud By Llermo",
        "imagen": "blackoud-by-llermo",
        "casa": "Blackoud",
        "precio": "375.000 COP",
        "disponibilidad": "Solo original",
        "descripcion": "Perfume Blackoud By Llermo de la casa Blackoud, conocido por su elegancia y sofisticación.",
        "aromas": "Amaderado"
    },
    {
        "id": 42,
        "nombre": "Blackoud Dubai Night",
        "imagen": "blackoud-dubai-night",
        "casa": "Blackoud",
        "precio": "375.000 COP",
        "disponibilidad": "Solo original",
        "descripcion": "Perfume Blackoud Dubai Night de la casa Blackoud, conocido por su elegancia y sofisticación.",
        "aromas": "Amaderado"
    },
    {
        "id": 43,
        "nombre": "Blackoud Latin Rose",
        "imagen": "blackoud-latin-rose",
        "casa": "Blackoud",
        "precio": "375.000 COP",
        "disponibilidad": "Solo original",
        "descripcion": "Perfume Blackoud Latin Rose de la casa Blackoud, conocido por su elegancia y sofisticación.",
        "aromas": "Amaderado"
    },
    {
        "id": 44,
        "nombre": "Blackoud Orient Rose",
        "imagen": "blackoud-orient-rose",
        "casa": "Blackoud",
        "precio": "375.000 COP",
        "disponibilidad": "Solo original",
        "descripcion": "Perfume Blackoud Orient Rose de la casa Blackoud, conocido por su elegancia y sofisticación.",
        "aromas": "Amaderado"
    },
    {
        "id": 45,
        "nombre": "Blackoud Oriental Elixir",
        "imagen": "blackoud-oriental-elixir",
        "casa": "Blackoud",
        "precio": "375.000 COP",
        "disponibilidad": "Solo original",
        "descripcion": "Perfume Blackoud Oriental Elixir de la casa Blackoud, conocido por su elegancia y sofisticación.",
        "aromas": "Amaderado"
    },
    {
        "id": 46,
        "nombre": "Blackoud Oud Noir",
        "imagen": "blackoud-oud-noir",
        "casa": "Blackoud",
        "precio": "375.000 COP",
        "disponibilidad": "Solo original",
        "descripcion": "Perfume Blackoud Oud Noir de la casa Blackoud, conocido por su elegancia y sofisticación.",
        "aromas": "Amaderado"
    },
    {
        "id": 47,
        "nombre": "Blackoud Oud Vanilla",
        "imagen": "blackoud-oud-vanilla",
        "casa": "Blackoud",
        "precio": "375.000 COP",
        "disponibilidad": "Solo original",
        "descripcion": "Perfume Blackoud Oud Vanilla de la casa Blackoud, conocido por su elegancia y sofisticación.",
        "aromas": "Amaderado"
    },
    {
        "id": 48,
        "nombre": "Blackoud VIP Carat",
        "imagen": "blackoud-vip-carat",
        "casa": "Blackoud",
        "precio": "375.000 COP",
        "disponibilidad": "Solo original",
        "descripcion": "Perfume Blackoud VIP Carat de la casa Blackoud, conocido por su elegancia y sofisticación.",
        "aromas": "Amaderado"
    },
    {
        "id": 49,
        "nombre": "Club de Nuit Intense ",
        "imagen": "club-de-nuit-intense-",
        "casa": "Club de Nuit",
        "precio": "285.000 COP",
        "disponibilidad": "Solo original",
        "descripcion": "Perfume Club de Nuit Intense  de la casa Club de Nuit, conocido por su elegancia y sofisticación.",
        "aromas": "Aroma variado"
    },
    {
        "id": 50,
        "nombre": "Club de Nuit Untold",
        "imagen": "club-de-nuit-untold",
        "casa": "Club de Nuit",
        "precio": "350.000 COP",
        "disponibilidad": "Solo original",
        "descripcion": "Perfume Club de Nuit Untold de la casa Club de Nuit, conocido por su elegancia y sofisticación.",
        "aromas": "Aroma variado"
    },
    {
        "id": 51,
        "nombre": "Club de Nuit Urban Man Elixir",
        "imagen": "club-de-nuit-urban-man-elixir",
        "casa": "Club de Nuit",
        "precio": "325.000 COP",
        "disponibilidad": "Solo original",
        "descripcion": "Perfume Club de Nuit Urban Man Elixir de la casa Club de Nuit, conocido por su elegancia y sofisticación.",
        "aromas": "Aroma variado"
    },
    {
        "id": 52,
        "nombre": "Delina",
        "imagen": "delina",
        "casa": "Delina",
        "precio": "1.380.000 COP",
        "disponibilidad": "Solo original",
        "descripcion": "Perfume Delina de la casa Delina, conocido por su elegancia y sofisticación.",
        "aromas": "Aroma variado"
    },
    {
        "id": 53,
        "nombre": "Delina Exclusif",
        "imagen": "delina-exclusif",
        "casa": "Delina",
        "precio": "1.490.000 COP",
        "disponibilidad": "Solo original",
        "descripcion": "Perfume Delina Exclusif de la casa Delina, conocido por su elegancia y sofisticación.",
        "aromas": "Aroma variado"
    },
    {
        "id": 54,
        "nombre": "Devier Acid Rain",
        "imagen": "devier-acid-rain",
        "casa": "Devier",
        "precio": "499.000 COP",
        "disponibilidad": "Solo original",
        "descripcion": "Perfume Devier Acid Rain de la casa Devier, conocido por su elegancia y sofisticación.",
        "aromas": "Aroma variado"
    },
    {
        "id": 55,
        "nombre": "Devier Amber Arabian",
        "imagen": "devier-amber-arabian",
        "casa": "Devier",
        "precio": "499.000 COP",
        "disponibilidad": "Solo original",
        "descripcion": "Perfume Devier Amber Arabian de la casa Devier, conocido por su elegancia y sofisticación.",
        "aromas": "Aroma variado"
    },
    {
        "id": 56,
        "nombre": "Devier Black Religion",
        "imagen": "devier-black-religion",
        "casa": "Devier",
        "precio": "499.000 COP",
        "disponibilidad": "Solo original",
        "descripcion": "Perfume Devier Black Religion de la casa Devier, conocido por su elegancia y sofisticación.",
        "aromas": "Aroma variado"
    },
    {
        "id": 57,
        "nombre": "Devier Deep Smoke",
        "imagen": "devier-deep-smoke",
        "casa": "Devier",
        "precio": "499.000 COP",
        "disponibilidad": "Solo original",
        "descripcion": "Perfume Devier Deep Smoke de la casa Devier, conocido por su elegancia y sofisticación.",
        "aromas": "Aroma variado"
    },
    {
        "id": 58,
        "nombre": "Devier Forgive Us",
        "imagen": "devier-forgive-us",
        "casa": "Devier",
        "precio": "499.000 COP",
        "disponibilidad": "Solo original",
        "descripcion": "Perfume Devier Forgive Us de la casa Devier, conocido por su elegancia y sofisticación.",
        "aromas": "Aroma variado"
    },
    {
        "id": 59,
        "nombre": "Devier Imagine",
        "imagen": "devier-imagine",
        "casa": "Devier",
        "precio": "499.000 COP",
        "disponibilidad": "Solo original",
        "descripcion": "Perfume Devier Imagine de la casa Devier, conocido por su elegancia y sofisticación.",
        "aromas": "Aroma variado"
    },
    {
        "id": 60,
        "nombre": "Devier Penth House",
        "imagen": "devier-penth-house",
        "casa": "Devier",
        "precio": "499.000 COP",
        "disponibilidad": "Solo original",
        "descripcion": "Perfume Devier Penth House de la casa Devier, conocido por su elegancia y sofisticación.",
        "aromas": "Aroma variado"
    },
    {
        "id": 61,
        "nombre": "Devier Sandal Oud",
        "imagen": "devier-sandal-oud",
        "casa": "Devier",
        "precio": "499.000 COP",
        "disponibilidad": "Solo original",
        "descripcion": "Perfume Devier Sandal Oud de la casa Devier, conocido por su elegancia y sofisticación.",
        "aromas": "Amaderado"
    },
    {
        "id": 62,
        "nombre": "Devier Spice Mexican",
        "imagen": "devier-spice-mexican",
        "casa": "Devier",
        "precio": "499.000 COP",
        "disponibilidad": "Solo original",
        "descripcion": "Perfume Devier Spice Mexican de la casa Devier, conocido por su elegancia y sofisticación.",
        "aromas": "Aroma variado"
    },
    {
        "id": 63,
        "nombre": "Devier Strong As Metal",
        "imagen": "devier-strong-as-metal",
        "casa": "Devier",
        "precio": "499.000 COP",
        "disponibilidad": "Solo original",
        "descripcion": "Perfume Devier Strong As Metal de la casa Devier, conocido por su elegancia y sofisticación.",
        "aromas": "Aroma variado"
    },
    {
        "id": 64,
        "nombre": "Emunah",
        "imagen": "emunah",
        "casa": "Emunah",
        "precio": "499.000 COP",
        "disponibilidad": "Solo original",
        "descripcion": "Perfume Emunah de la casa Emunah, conocido por su elegancia y sofisticación.",
        "aromas": "Aroma variado"
    },
    {
        "id": 65,
        "nombre": "Gevill Aphrodisiaque Sexxx",
        "imagen": "gevill-aphrodisiaque-sexxx",
        "casa": "Gevill",
        "precio": "1.020.000 COP",
        "disponibilidad": "Solo original",
        "descripcion": "Perfume Gevill Aphrodisiaque Sexxx de la casa Gevill, conocido por su elegancia y sofisticación.",
        "aromas": "Aroma variado"
    },
    {
        "id": 66,
        "nombre": "Gevill Aqua de Paris",
        "imagen": "gevill-aqua-de-paris",
        "casa": "Gevill",
        "precio": "1.020.000 COP",
        "disponibilidad": "Solo original",
        "descripcion": "Perfume Gevill Aqua de Paris de la casa Gevill, conocido por su elegancia y sofisticación.",
        "aromas": "Aroma variado"
    },
    {
        "id": 67,
        "nombre": "Gevill Attraction Fatale",
        "imagen": "gevill-attraction-fatale",
        "casa": "Gevill",
        "precio": "1.020.000 COP",
        "disponibilidad": "Solo original",
        "descripcion": "Perfume Gevill Attraction Fatale de la casa Gevill, conocido por su elegancia y sofisticación.",
        "aromas": "Aroma variado"
    },
    {
        "id": 68,
        "nombre": "Gevill Beso Dragon",
        "imagen": "gevill-beso-dragon",
        "casa": "Gevill",
        "precio": "1.020.000 COP",
        "disponibilidad": "Solo original",
        "descripcion": "Perfume Gevill Beso Dragon de la casa Gevill, conocido por su elegancia y sofisticación.",
        "aromas": "Aroma variado"
    },
    {
        "id": 69,
        "nombre": "Gevill Centifolia D´France",
        "imagen": "gevill-centifolia-d´france",
        "casa": "Gevill",
        "precio": "1.020.000 COP",
        "disponibilidad": "Solo original",
        "descripcion": "Perfume Gevill Centifolia D´France de la casa Gevill, conocido por su elegancia y sofisticación.",
        "aromas": "Aroma variado"
    },
    {
        "id": 70,
        "nombre": "Gevill Creation Mysteriouse",
        "imagen": "gevill-creation-mysteriouse",
        "casa": "Gevill",
        "precio": "1.020.000 COP",
        "disponibilidad": "Solo original",
        "descripcion": "Perfume Gevill Creation Mysteriouse de la casa Gevill, conocido por su elegancia y sofisticación.",
        "aromas": "Aroma variado"
    },
    {
        "id": 71,
        "nombre": "Gevill Fantome Romantique",
        "imagen": "gevill-fantome-romantique",
        "casa": "Gevill",
        "precio": "1.020.000 COP",
        "disponibilidad": "Solo original",
        "descripcion": "Perfume Gevill Fantome Romantique de la casa Gevill, conocido por su elegancia y sofisticación.",
        "aromas": "Aroma variado"
    },
    {
        "id": 72,
        "nombre": "Gevill Fortune",
        "imagen": "gevill-fortune",
        "casa": "Gevill",
        "precio": "1.020.000 COP",
        "disponibilidad": "Solo original",
        "descripcion": "Perfume Gevill Fortune de la casa Gevill, conocido por su elegancia y sofisticación.",
        "aromas": "Aroma variado"
    },
    {
        "id": 73,
        "nombre": "Gevill Kamasutra",
        "imagen": "gevill-kamasutra",
        "casa": "Gevill",
        "precio": "1.020.000 COP",
        "disponibilidad": "Solo original",
        "descripcion": "Perfume Gevill Kamasutra de la casa Gevill, conocido por su elegancia y sofisticación.",
        "aromas": "Aroma variado"
    },
    {
        "id": 74,
        "nombre": "Gevill King Tutankhamun",
        "imagen": "gevill-king-tutankhamun",
        "casa": "Gevill",
        "precio": "1.550.000 COP",
        "disponibilidad": "Solo original",
        "descripcion": "Perfume Gevill King Tutankhamun de la casa Gevill, conocido por su elegancia y sofisticación.",
        "aromas": "Aroma variado"
    },
    {
        "id": 75,
        "nombre": "Gevill L´ange Santorin",
        "imagen": "gevill-l´ange-santorin",
        "casa": "Gevill",
        "precio": "1.020.000 COP",
        "disponibilidad": "Solo original",
        "descripcion": "Perfume Gevill L´ange Santorin de la casa Gevill, conocido por su elegancia y sofisticación.",
        "aromas": "Aroma variado"
    },
    {
        "id": 76,
        "nombre": "Gevill L´art Cupido",
        "imagen": "gevill-l´art-cupido",
        "casa": "Gevill",
        "precio": "1.020.000 COP",
        "disponibilidad": "Solo original",
        "descripcion": "Perfume Gevill L´art Cupido de la casa Gevill, conocido por su elegancia y sofisticación.",
        "aromas": "Aroma variado"
    },
    {
        "id": 77,
        "nombre": "Gevill L´or Quimbaya",
        "imagen": "gevill-l´or-quimbaya",
        "casa": "Gevill",
        "precio": "1.750.000 COP",
        "disponibilidad": "Solo original",
        "descripcion": "Perfume Gevill L´or Quimbaya de la casa Gevill, conocido por su elegancia y sofisticación.",
        "aromas": "Aroma variado"
    },
    {
        "id": 78,
        "nombre": "Gevill Majestic",
        "imagen": "gevill-majestic",
        "casa": "Gevill",
        "precio": "1.020.000 COP",
        "disponibilidad": "Solo original",
        "descripcion": "Perfume Gevill Majestic de la casa Gevill, conocido por su elegancia y sofisticación.",
        "aromas": "Aroma variado"
    },
    {
        "id": 79,
        "nombre": "Gevill Millionaire",
        "imagen": "gevill-millionaire",
        "casa": "Gevill",
        "precio": "1.020.000 COP",
        "disponibilidad": "Solo original",
        "descripcion": "Perfume Gevill Millionaire de la casa Gevill, conocido por su elegancia y sofisticación.",
        "aromas": "Aroma variado"
    },
    {
        "id": 80,
        "nombre": "Gevill Rose Erotique",
        "imagen": "gevill-rose-erotique",
        "casa": "Gevill",
        "precio": "1.020.000 COP",
        "disponibilidad": "Solo original",
        "descripcion": "Perfume Gevill Rose Erotique de la casa Gevill, conocido por su elegancia y sofisticación.",
        "aromas": "Floral"
    },
    {
        "id": 81,
        "nombre": "Gevill Rose Mystique",
        "imagen": "gevill-rose-mystique",
        "casa": "Gevill",
        "precio": "1.020.000 COP",
        "disponibilidad": "Solo original",
        "descripcion": "Perfume Gevill Rose Mystique de la casa Gevill, conocido por su elegancia y sofisticación.",
        "aromas": "Floral"
    },
    {
        "id": 82,
        "nombre": "Gevill Royal Amber",
        "imagen": "gevill-royal-amber",
        "casa": "Gevill",
        "precio": "1.020.000 COP",
        "disponibilidad": "Solo original",
        "descripcion": "Perfume Gevill Royal Amber de la casa Gevill, conocido por su elegancia y sofisticación.",
        "aromas": "Aroma variado"
    },
    {
        "id": 83,
        "nombre": "Gevill Sahara Oud",
        "imagen": "gevill-sahara-oud",
        "casa": "Gevill",
        "precio": "1.020.000 COP",
        "disponibilidad": "Solo original",
        "descripcion": "Perfume Gevill Sahara Oud de la casa Gevill, conocido por su elegancia y sofisticación.",
        "aromas": "Amaderado"
    },
    {
        "id": 84,
        "nombre": "Gevill Santal Rose Des Princess",
        "imagen": "gevill-santal-rose-des-princess",
        "casa": "Gevill",
        "precio": "1.020.000 COP",
        "disponibilidad": "Solo original",
        "descripcion": "Perfume Gevill Santal Rose Des Princess de la casa Gevill, conocido por su elegancia y sofisticación.",
        "aromas": "Floral"
    },
    {
        "id": 85,
        "nombre": "Gevill Sheng Long",
        "imagen": "gevill-sheng-long",
        "casa": "Gevill",
        "precio": "1.020.000 COP",
        "disponibilidad": "Solo original",
        "descripcion": "Perfume Gevill Sheng Long de la casa Gevill, conocido por su elegancia y sofisticación.",
        "aromas": "Aroma variado"
    },
    {
        "id": 86,
        "nombre": "Gevill Spirit D´Amour",
        "imagen": "gevill-spirit-d´amour",
        "casa": "Gevill",
        "precio": "1.020.000 COP",
        "disponibilidad": "Solo original",
        "descripcion": "Perfume Gevill Spirit D´Amour de la casa Gevill, conocido por su elegancia y sofisticación.",
        "aromas": "Aroma variado"
    },
    {
        "id": 87,
        "nombre": "ILMIN IL AME",
        "imagen": "ilmin-il-ame",
        "casa": "ILMIN",
        "precio": "619.000 COP",
        "disponibilidad": "Solo original",
        "descripcion": "Perfume ILMIN IL AME de la casa ILMIN, conocido por su elegancia y sofisticación.",
        "aromas": "Aroma variado"
    },
    {
        "id": 88,
        "nombre": "ILMIN IL ARTE",
        "imagen": "ilmin-il-arte",
        "casa": "ILMIN",
        "precio": "619.000 COP",
        "disponibilidad": "Solo original",
        "descripcion": "Perfume ILMIN IL ARTE de la casa ILMIN, conocido por su elegancia y sofisticación.",
        "aromas": "Aroma variado"
    },
    {
        "id": 89,
        "nombre": "ILMIN IL BEE",
        "imagen": "ilmin-il-bee",
        "casa": "ILMIN",
        "precio": "619.000 COP",
        "disponibilidad": "Solo original",
        "descripcion": "Perfume ILMIN IL BEE de la casa ILMIN, conocido por su elegancia y sofisticación.",
        "aromas": "Aroma variado"
    },
    {
        "id": 90,
        "nombre": "ILMIN IL BORDEAUX",
        "imagen": "ilmin-il-bordeaux",
        "casa": "ILMIN",
        "precio": "619.000 COP",
        "disponibilidad": "Solo original",
        "descripcion": "Perfume ILMIN IL BORDEAUX de la casa ILMIN, conocido por su elegancia y sofisticación.",
        "aromas": "Aroma variado"
    },
    {
        "id": 91,
        "nombre": "ILMIN IL DOLCE",
        "imagen": "ilmin-il-dolce",
        "casa": "ILMIN",
        "precio": "619.000 COP",
        "disponibilidad": "Solo original",
        "descripcion": "Perfume ILMIN IL DOLCE de la casa ILMIN, conocido por su elegancia y sofisticación.",
        "aromas": "Aroma variado"
    },
    {
        "id": 92,
        "nombre": "ILMIN IL EGO",
        "imagen": "ilmin-il-ego",
        "casa": "ILMIN",
        "precio": "619.000 COP",
        "disponibilidad": "Solo original",
        "descripcion": "Perfume ILMIN IL EGO de la casa ILMIN, conocido por su elegancia y sofisticación.",
        "aromas": "Aroma variado"
    },
    {
        "id": 93,
        "nombre": "ILMIN IL EROTIQUE",
        "imagen": "ilmin-il-erotique",
        "casa": "ILMIN",
        "precio": "619.000 COP",
        "disponibilidad": "Solo original",
        "descripcion": "Perfume ILMIN IL EROTIQUE de la casa ILMIN, conocido por su elegancia y sofisticación.",
        "aromas": "Aroma variado"
    },
    {
        "id": 94,
        "nombre": "ILMIN IL FEMME",
        "imagen": "ilmin-il-femme",
        "casa": "ILMIN",
        "precio": "619.000 COP",
        "disponibilidad": "Solo original",
        "descripcion": "Perfume ILMIN IL FEMME de la casa ILMIN, conocido por su elegancia y sofisticación.",
        "aromas": "Aroma variado"
    },
    {
        "id": 95,
        "nombre": "ILMIN IL KAKUNO",
        "imagen": "ilmin-il-kakuno",
        "casa": "ILMIN",
        "precio": "619.000 COP",
        "disponibilidad": "Solo original",
        "descripcion": "Perfume ILMIN IL KAKUNO de la casa ILMIN, conocido por su elegancia y sofisticación.",
        "aromas": "Aroma variado"
    },
    {
        "id": 96,
        "nombre": "ILMIN IL LAVISH",
        "imagen": "ilmin-il-lavish",
        "casa": "ILMIN",
        "precio": "619.000 COP",
        "disponibilidad": "Solo original",
        "descripcion": "Perfume ILMIN IL LAVISH de la casa ILMIN, conocido por su elegancia y sofisticación.",
        "aromas": "Aroma variado"
    },
    {
        "id": 97,
        "nombre": "ILMIN IL LONVE",
        "imagen": "ilmin-il-lonve",
        "casa": "ILMIN",
        "precio": "619.000 COP",
        "disponibilidad": "Solo original",
        "descripcion": "Perfume ILMIN IL LONVE de la casa ILMIN, conocido por su elegancia y sofisticación.",
        "aromas": "Aroma variado"
    },
    {
        "id": 98,
        "nombre": "ILMIN IL MAGNIFICENT",
        "imagen": "ilmin-il-magnificent",
        "casa": "ILMIN",
        "precio": "619.000 COP",
        "disponibilidad": "Solo original",
        "descripcion": "Perfume ILMIN IL MAGNIFICENT de la casa ILMIN, conocido por su elegancia y sofisticación.",
        "aromas": "Aroma variado"
    },
    {
        "id": 99,
        "nombre": "ILMIN IL MALE",
        "imagen": "ilmin-il-male",
        "casa": "ILMIN",
        "precio": "619.000 COP",
        "disponibilidad": "Solo original",
        "descripcion": "Perfume ILMIN IL MALE de la casa ILMIN, conocido por su elegancia y sofisticación.",
        "aromas": "Aroma variado"
    },
    {
        "id": 100,
        "nombre": "ILMIN IL MEXICO",
        "imagen": "ilmin-il-mexico",
        "casa": "ILMIN",
        "precio": "619.000 COP",
        "disponibilidad": "Solo original",
        "descripcion": "Perfume ILMIN IL MEXICO de la casa ILMIN, conocido por su elegancia y sofisticación.",
        "aromas": "Aroma variado"
    },
    {
        "id": 101,
        "nombre": "ILMIN IL OOMPH",
        "imagen": "ilmin-il-oomph",
        "casa": "ILMIN",
        "precio": "619.000 COP",
        "disponibilidad": "Solo original",
        "descripcion": "Perfume ILMIN IL OOMPH de la casa ILMIN, conocido por su elegancia y sofisticación.",
        "aromas": "Aroma variado"
    },
    {
        "id": 102,
        "nombre": "ILMIN IL ORGASME",
        "imagen": "ilmin-il-orgasme",
        "casa": "ILMIN",
        "precio": "619.000 COP",
        "disponibilidad": "Solo original",
        "descripcion": "Perfume ILMIN IL ORGASME de la casa ILMIN, conocido por su elegancia y sofisticación.",
        "aromas": "Aroma variado"
    },
    {
        "id": 103,
        "nombre": "ILMIN IL ROSO",
        "imagen": "ilmin-il-roso",
        "casa": "ILMIN",
        "precio": "619.000 COP",
        "disponibilidad": "Solo original",
        "descripcion": "Perfume ILMIN IL ROSO de la casa ILMIN, conocido por su elegancia y sofisticación.",
        "aromas": "Aroma variado"
    },
    {
        "id": 104,
        "nombre": "ILMIN IL SATIVA",
        "imagen": "ilmin-il-sativa",
        "casa": "ILMIN",
        "precio": "619.000 COP",
        "disponibilidad": "Solo original",
        "descripcion": "Perfume ILMIN IL SATIVA de la casa ILMIN, conocido por su elegancia y sofisticación.",
        "aromas": "Aroma variado"
    },
    {
        "id": 105,
        "nombre": "ILMIN IL SEXUEL",
        "imagen": "ilmin-il-sexuel",
        "casa": "ILMIN",
        "precio": "619.000 COP",
        "disponibilidad": "Solo original",
        "descripcion": "Perfume ILMIN IL SEXUEL de la casa ILMIN, conocido por su elegancia y sofisticación.",
        "aromas": "Aroma variado"
    },
    {
        "id": 106,
        "nombre": "ILMIN IL SNOB",
        "imagen": "ilmin-il-snob",
        "casa": "ILMIN",
        "precio": "619.000 COP",
        "disponibilidad": "Solo original",
        "descripcion": "Perfume ILMIN IL SNOB de la casa ILMIN, conocido por su elegancia y sofisticación.",
        "aromas": "Aroma variado"
    },
    {
        "id": 107,
        "nombre": "ILMIN IL SONT",
        "imagen": "ilmin-il-sont",
        "casa": "ILMIN",
        "precio": "619.000 COP",
        "disponibilidad": "Solo original",
        "descripcion": "Perfume ILMIN IL SONT de la casa ILMIN, conocido por su elegancia y sofisticación.",
        "aromas": "Aroma variado"
    },
    {
        "id": 108,
        "nombre": "ILMIN IL VITA",
        "imagen": "ilmin-il-vita",
        "casa": "ILMIN",
        "precio": "619.000 COP",
        "disponibilidad": "Solo original",
        "descripcion": "Perfume ILMIN IL VITA de la casa ILMIN, conocido por su elegancia y sofisticación.",
        "aromas": "Aroma variado"
    },
    {
        "id": 109,
        "nombre": "ILMIN IL VOSS",
        "imagen": "ilmin-il-voss",
        "casa": "ILMIN",
        "precio": "619.000 COP",
        "disponibilidad": "Solo original",
        "descripcion": "Perfume ILMIN IL VOSS de la casa ILMIN, conocido por su elegancia y sofisticación.",
        "aromas": "Aroma variado"
    },
    {
        "id": 110,
        "nombre": "Initio Atomic Rose",
        "imagen": "initio-atomic-rose",
        "casa": "Initio",
        "precio": "1.390.000 COP",
        "disponibilidad": "Solo original",
        "descripcion": "Perfume Initio Atomic Rose de la casa Initio, conocido por su elegancia y sofisticación.",
        "aromas": "Floral"
    },
    {
        "id": 111,
        "nombre": "Initio High Frequency",
        "imagen": "initio-high-frequency",
        "casa": "Initio",
        "precio": "1.390.000 COP",
        "disponibilidad": "Solo original",
        "descripcion": "Perfume Initio High Frequency de la casa Initio, conocido por su elegancia y sofisticación.",
        "aromas": "Aroma variado"
    },
    {
        "id": 112,
        "nombre": "Initio Oud For Greatness",
        "imagen": "initio-oud-for-greatness",
        "casa": "Initio",
        "precio": "1.450.000 COP",
        "disponibilidad": "Solo original",
        "descripcion": "Perfume Initio Oud For Greatness de la casa Initio, conocido por su elegancia y sofisticación.",
        "aromas": "Amaderado"
    },
    {
        "id": 113,
        "nombre": "Initio Oud For Happiness",
        "imagen": "initio-oud-for-happiness",
        "casa": "Initio",
        "precio": "1.450.000 COP",
        "disponibilidad": "Solo original",
        "descripcion": "Perfume Initio Oud For Happiness de la casa Initio, conocido por su elegancia y sofisticación.",
        "aromas": "Amaderado"
    },
    {
        "id": 114,
        "nombre": "Initio Psychedelic Love",
        "imagen": "initio-psychedelic-love",
        "casa": "Initio",
        "precio": "1.390.000 COP",
        "disponibilidad": "Solo original",
        "descripcion": "Perfume Initio Psychedelic Love de la casa Initio, conocido por su elegancia y sofisticación.",
        "aromas": "Aroma variado"
    },
    {
        "id": 115,
        "nombre": "Initio Rehab",
        "imagen": "initio-rehab",
        "casa": "Initio",
        "precio": "1.390.000 COP",
        "disponibilidad": "Solo original",
        "descripcion": "Perfume Initio Rehab de la casa Initio, conocido por su elegancia y sofisticación.",
        "aromas": "Aroma variado"
    },
    {
        "id": 116,
        "nombre": "Initio Side Effect",
        "imagen": "initio-side-effect",
        "casa": "Initio",
        "precio": "1.390.000 COP",
        "disponibilidad": "Solo original",
        "descripcion": "Perfume Initio Side Effect de la casa Initio, conocido por su elegancia y sofisticación.",
        "aromas": "Aroma variado"
    },
    {
        "id": 117,
        "nombre": "Jean Paul Gaultier Ultramale ",
        "imagen": "jean-paul-gaultier-ultramale-",
        "casa": "Jean Paul Gaultier",
        "precio": "500.000 COP",
        "disponibilidad": "Solo original",
        "descripcion": "Perfume Jean Paul Gaultier Ultramale  de la casa Jean Paul Gaultier, conocido por su elegancia y sofisticación.",
        "aromas": "Aroma variado"
    },
    {
        "id": 118,
        "nombre": "Jean Paul Gaultier Le Male Elixir",
        "imagen": "jean-paul-gaultier-le-male-elixir",
        "casa": "Jean Paul Gaultier",
        "precio": "730.000 COP",
        "disponibilidad": "Solo original",
        "descripcion": "Perfume Jean Paul Gaultier Le Male Elixir de la casa Jean Paul Gaultier, conocido por su elegancia y sofisticación.",
        "aromas": "Aroma variado"
    },
    {
        "id": 119,
        "nombre": "Jean Paul Gaultier Le Male Le Parfum",
        "imagen": "jean-paul-gaultier-le-male-le-parfum",
        "casa": "Jean Paul Gaultier",
        "precio": "720.000 COP",
        "disponibilidad": "Solo original",
        "descripcion": "Perfume Jean Paul Gaultier Le Male Le Parfum de la casa Jean Paul Gaultier, conocido por su elegancia y sofisticación.",
        "aromas": "Aroma variado"
    },
    {
        "id": 120,
        "nombre": "Lattafa Ajwad",
        "imagen": "lattafa-ajwad",
        "casa": "Lattafa",
        "precio": "270.000 COP",
        "disponibilidad": "Solo original",
        "descripcion": "Perfume Lattafa Ajwad de la casa Lattafa, conocido por su elegancia y sofisticación.",
        "aromas": "Aroma variado"
    },
    {
        "id": 121,
        "nombre": "Lattafa Ajwad Pink To Pink",
        "imagen": "lattafa-ajwad-pink-to-pink",
        "casa": "Lattafa",
        "precio": "260.000 COP",
        "disponibilidad": "Solo original",
        "descripcion": "Perfume Lattafa Ajwad Pink To Pink de la casa Lattafa, conocido por su elegancia y sofisticación.",
        "aromas": "Aroma variado"
    },
    {
        "id": 122,
        "nombre": "Lattafa Al Noble Safeer",
        "imagen": "lattafa-al-noble-safeer",
        "casa": "Lattafa",
        "precio": "270.000 COP",
        "disponibilidad": "Solo original",
        "descripcion": "Perfume Lattafa Al Noble Safeer de la casa Lattafa, conocido por su elegancia y sofisticación.",
        "aromas": "Aroma variado"
    },
    {
        "id": 123,
        "nombre": "Lattafa Al Noble Wazeer",
        "imagen": "lattafa-al-noble-wazeer",
        "casa": "Lattafa",
        "precio": "270.000 COP",
        "disponibilidad": "Solo original",
        "descripcion": "Perfume Lattafa Al Noble Wazeer de la casa Lattafa, conocido por su elegancia y sofisticación.",
        "aromas": "Aroma variado"
    },
    {
        "id": 124,
        "nombre": "Lattafa Amethyst",
        "imagen": "lattafa-amethyst",
        "casa": "Lattafa",
        "precio": "275.000 COP",
        "disponibilidad": "Solo original",
        "descripcion": "Perfume Lattafa Amethyst de la casa Lattafa, conocido por su elegancia y sofisticación.",
        "aromas": "Aroma variado"
    },
    {
        "id": 125,
        "nombre": "Lattafa Asad",
        "imagen": "lattafa-asad",
        "casa": "Lattafa",
        "precio": "270.000 COP",
        "disponibilidad": "Solo original",
        "descripcion": "Perfume Lattafa Asad de la casa Lattafa, conocido por su elegancia y sofisticación.",
        "aromas": "Aroma variado"
    },
    {
        "id": 126,
        "nombre": "Lattafa Ethernal Oud",
        "imagen": "lattafa-ethernal-oud",
        "casa": "Lattafa",
        "precio": "350.000 COP",
        "disponibilidad": "Solo original",
        "descripcion": "Perfume Lattafa Ethernal Oud de la casa Lattafa, conocido por su elegancia y sofisticación.",
        "aromas": "Amaderado"
    },
    {
        "id": 127,
        "nombre": "Lattafa Haya",
        "imagen": "lattafa-haya",
        "casa": "Lattafa",
        "precio": "290.000 COP",
        "disponibilidad": "Solo original",
        "descripcion": "Perfume Lattafa Haya de la casa Lattafa, conocido por su elegancia y sofisticación.",
        "aromas": "Aroma variado"
    },
    {
        "id": 128,
        "nombre": "Lattafa Honor & Glory",
        "imagen": "lattafa-honor-&-glory",
        "casa": "Lattafa",
        "precio": "295.000 COP",
        "disponibilidad": "Solo original",
        "descripcion": "Perfume Lattafa Honor & Glory de la casa Lattafa, conocido por su elegancia y sofisticación.",
        "aromas": "Aroma variado"
    },
    {
        "id": 129,
        "nombre": "Lattafa Khamrah",
        "imagen": "lattafa-khamrah",
        "casa": "Lattafa",
        "precio": "289.000 COP",
        "disponibilidad": "Solo original",
        "descripcion": "Perfume Lattafa Khamrah de la casa Lattafa, conocido por su elegancia y sofisticación.",
        "aromas": "Aroma variado"
    },
    {
        "id": 130,
        "nombre": "Lattafa Lail Maleki",
        "imagen": "lattafa-lail-maleki",
        "casa": "Lattafa",
        "precio": "240.000 COP",
        "disponibilidad": "Solo original",
        "descripcion": "Perfume Lattafa Lail Maleki de la casa Lattafa, conocido por su elegancia y sofisticación.",
        "aromas": "Aroma variado"
    },
    {
        "id": 131,
        "nombre": "Lattafa Mayar",
        "imagen": "lattafa-mayar",
        "casa": "Lattafa",
        "precio": "270.000 COP",
        "disponibilidad": "Solo original",
        "descripcion": "Perfume Lattafa Mayar de la casa Lattafa, conocido por su elegancia y sofisticación.",
        "aromas": "Aroma variado"
    },
    {
        "id": 132,
        "nombre": "Lattafa Oud For Glory",
        "imagen": "lattafa-oud-for-glory",
        "casa": "Lattafa",
        "precio": "280.000 COP",
        "disponibilidad": "Solo original",
        "descripcion": "Perfume Lattafa Oud For Glory de la casa Lattafa, conocido por su elegancia y sofisticación.",
        "aromas": "Amaderado"
    },
    {
        "id": 133,
        "nombre": "Lattafa Pride Al Qiam Gold",
        "imagen": "lattafa-pride-al-qiam-gold",
        "casa": "Lattafa",
        "precio": "299.000 COP",
        "disponibilidad": "Solo original",
        "descripcion": "Perfume Lattafa Pride Al Qiam Gold de la casa Lattafa, conocido por su elegancia y sofisticación.",
        "aromas": "Aroma variado"
    },
    {
        "id": 134,
        "nombre": "Lattafa Pride Ansaam Gold",
        "imagen": "lattafa-pride-ansaam-gold",
        "casa": "Lattafa",
        "precio": "299.000 COP",
        "disponibilidad": "Solo original",
        "descripcion": "Perfume Lattafa Pride Ansaam Gold de la casa Lattafa, conocido por su elegancia y sofisticación.",
        "aromas": "Aroma variado"
    },
    {
        "id": 135,
        "nombre": "Lattafa Pride Fakhar Gold",
        "imagen": "lattafa-pride-fakhar-gold",
        "casa": "Lattafa",
        "precio": "270.000 COP",
        "disponibilidad": "Solo original",
        "descripcion": "Perfume Lattafa Pride Fakhar Gold de la casa Lattafa, conocido por su elegancia y sofisticación.",
        "aromas": "Aroma variado"
    },
    {
        "id": 136,
        "nombre": "Lattafa Pride Fakhar Man",
        "imagen": "lattafa-pride-fakhar-man",
        "casa": "Lattafa",
        "precio": "270.000 COP",
        "disponibilidad": "Solo original",
        "descripcion": "Perfume Lattafa Pride Fakhar Man de la casa Lattafa, conocido por su elegancia y sofisticación.",
        "aromas": "Aroma variado"
    },
    {
        "id": 137,
        "nombre": "Lattafa Pride Fakhar Woman",
        "imagen": "lattafa-pride-fakhar-woman",
        "casa": "Lattafa",
        "precio": "270.000 COP",
        "disponibilidad": "Solo original",
        "descripcion": "Perfume Lattafa Pride Fakhar Woman de la casa Lattafa, conocido por su elegancia y sofisticación.",
        "aromas": "Aroma variado"
    },
    {
        "id": 138,
        "nombre": "Lattafa Pride Shaheen Gold",
        "imagen": "lattafa-pride-shaheen-gold",
        "casa": "Lattafa",
        "precio": "305.000 COP",
        "disponibilidad": "Solo original",
        "descripcion": "Perfume Lattafa Pride Shaheen Gold de la casa Lattafa, conocido por su elegancia y sofisticación.",
        "aromas": "Aroma variado"
    },
    {
        "id": 139,
        "nombre": "Lattafa Qaed Al Fursan",
        "imagen": "lattafa-qaed-al-fursan",
        "casa": "Lattafa",
        "precio": "250.000 COP",
        "disponibilidad": "Solo original",
        "descripcion": "Perfume Lattafa Qaed Al Fursan de la casa Lattafa, conocido por su elegancia y sofisticación.",
        "aromas": "Aroma variado"
    },
    {
        "id": 140,
        "nombre": "Lattafa Qaed Al Fursan Unlimited",
        "imagen": "lattafa-qaed-al-fursan-unlimited",
        "casa": "Lattafa",
        "precio": "250.000 COP",
        "disponibilidad": "Solo original",
        "descripcion": "Perfume Lattafa Qaed Al Fursan Unlimited de la casa Lattafa, conocido por su elegancia y sofisticación.",
        "aromas": "Aroma variado"
    },
    {
        "id": 141,
        "nombre": "Lattafa Saakena",
        "imagen": "lattafa-saakena",
        "casa": "Lattafa",
        "precio": "290.000 COP",
        "disponibilidad": "Solo original",
        "descripcion": "Perfume Lattafa Saakena de la casa Lattafa, conocido por su elegancia y sofisticación.",
        "aromas": "Aroma variado"
    },
    {
        "id": 142,
        "nombre": "Lattafa Sublime",
        "imagen": "lattafa-sublime",
        "casa": "Lattafa",
        "precio": "299.000 COP",
        "disponibilidad": "Solo original",
        "descripcion": "Perfume Lattafa Sublime de la casa Lattafa, conocido por su elegancia y sofisticación.",
        "aromas": "Aroma variado"
    },
    {
        "id": 143,
        "nombre": "Lattafa Teriaq",
        "imagen": "lattafa-teriaq",
        "casa": "Lattafa",
        "precio": "305.000 COP",
        "disponibilidad": "Solo original",
        "descripcion": "Perfume Lattafa Teriaq de la casa Lattafa, conocido por su elegancia y sofisticación.",
        "aromas": "Aroma variado"
    },
    {
        "id": 144,
        "nombre": "Lattafa Yara",
        "imagen": "lattafa-yara",
        "casa": "Lattafa",
        "precio": "290.000 COP",
        "disponibilidad": "Solo original",
        "descripcion": "Perfume Lattafa Yara de la casa Lattafa, conocido por su elegancia y sofisticación.",
        "aromas": "Aroma variado"
    },
    {
        "id": 145,
        "nombre": "Lattafa Yara Moi",
        "imagen": "lattafa-yara-moi",
        "casa": "Lattafa",
        "precio": "280.000 COP",
        "disponibilidad": "Solo original",
        "descripcion": "Perfume Lattafa Yara Moi de la casa Lattafa, conocido por su elegancia y sofisticación.",
        "aromas": "Aroma variado"
    },
    {
        "id": 146,
        "nombre": "Lattafa Yara Tous",
        "imagen": "lattafa-yara-tous",
        "casa": "Lattafa",
        "precio": "280.000 COP",
        "disponibilidad": "Solo original",
        "descripcion": "Perfume Lattafa Yara Tous de la casa Lattafa, conocido por su elegancia y sofisticación.",
        "aromas": "Aroma variado"
    },
    {
        "id": 147,
        "nombre": "Maison Alhambra Delilah",
        "imagen": "maison-alhambra-delilah",
        "casa": "Maison",
        "precio": "250.000 COP",
        "disponibilidad": "Solo original",
        "descripcion": "Perfume Maison Alhambra Delilah de la casa Maison, conocido por su elegancia y sofisticación.",
        "aromas": "Aroma variado"
    },
    {
        "id": 148,
        "nombre": "Mancera Aoud Café",
        "imagen": "mancera-aoud-café",
        "casa": "Mancera",
        "precio": "520.000 COP",
        "disponibilidad": "Solo original",
        "descripcion": "Perfume Mancera Aoud Café de la casa Mancera, conocido por su elegancia y sofisticación.",
        "aromas": "Amaderado"
    },
    {
        "id": 149,
        "nombre": "Mancera Cedrat Boise",
        "imagen": "mancera-cedrat-boise",
        "casa": "Mancera",
        "precio": "599.000 COP",
        "disponibilidad": "Solo original",
        "descripcion": "Perfume Mancera Cedrat Boise de la casa Mancera, conocido por su elegancia y sofisticación.",
        "aromas": "Aroma variado"
    },
    {
        "id": 150,
        "nombre": "Mancera Instant Crush",
        "imagen": "mancera-instant-crush",
        "casa": "Mancera",
        "precio": "599.000 COP",
        "disponibilidad": "Solo original",
        "descripcion": "Perfume Mancera Instant Crush de la casa Mancera, conocido por su elegancia y sofisticación.",
        "aromas": "Aroma variado"
    },
    {
        "id": 151,
        "nombre": "Mancera Red Tobacco",
        "imagen": "mancera-red-tobacco",
        "casa": "Mancera",
        "precio": "599.000 COP",
        "disponibilidad": "Solo original",
        "descripcion": "Perfume Mancera Red Tobacco de la casa Mancera, conocido por su elegancia y sofisticación.",
        "aromas": "Aroma variado"
    },
    {
        "id": 152,
        "nombre": "Mancera Roses Vanille",
        "imagen": "mancera-roses-vanille",
        "casa": "Mancera",
        "precio": "599.000 COP",
        "disponibilidad": "Solo original",
        "descripcion": "Perfume Mancera Roses Vanille de la casa Mancera, conocido por su elegancia y sofisticación.",
        "aromas": "Floral"
    },
    {
        "id": 153,
        "nombre": "Metropolis Green Valley Village",
        "imagen": "metropolis-green-valley-village",
        "casa": "Metropolis",
        "precio": "270.000 COP",
        "disponibilidad": "Solo original",
        "descripcion": "Perfume Metropolis Green Valley Village de la casa Metropolis, conocido por su elegancia y sofisticación.",
        "aromas": "Aroma variado"
    },
    {
        "id": 154,
        "nombre": "Metropolis Night Party",
        "imagen": "metropolis-night-party",
        "casa": "Metropolis",
        "precio": "270.000 COP",
        "disponibilidad": "Solo original",
        "descripcion": "Perfume Metropolis Night Party de la casa Metropolis, conocido por su elegancia y sofisticación.",
        "aromas": "Aroma variado"
    },
    {
        "id": 155,
        "nombre": "Metropolis Rock Street",
        "imagen": "metropolis-rock-street",
        "casa": "Metropolis",
        "precio": "270.000 COP",
        "disponibilidad": "Solo original",
        "descripcion": "Perfume Metropolis Rock Street de la casa Metropolis, conocido por su elegancia y sofisticación.",
        "aromas": "Aroma variado"
    },
    {
        "id": 156,
        "nombre": "Montale Arabians",
        "imagen": "montale-arabians",
        "casa": "Montale",
        "precio": "560.000 COP",
        "disponibilidad": "Solo original",
        "descripcion": "Perfume Montale Arabians de la casa Montale, conocido por su elegancia y sofisticación.",
        "aromas": "Aroma variado"
    },
    {
        "id": 157,
        "nombre": "Montale Arabians Tonka",
        "imagen": "montale-arabians-tonka",
        "casa": "Montale",
        "precio": "629.000 COP",
        "disponibilidad": "Solo original",
        "descripcion": "Perfume Montale Arabians Tonka de la casa Montale, conocido por su elegancia y sofisticación.",
        "aromas": "Aroma variado"
    },
    {
        "id": 158,
        "nombre": "Montale Dark Purple",
        "imagen": "montale-dark-purple",
        "casa": "Montale",
        "precio": "560.000 COP",
        "disponibilidad": "Solo original",
        "descripcion": "Perfume Montale Dark Purple de la casa Montale, conocido por su elegancia y sofisticación.",
        "aromas": "Aroma variado"
    },
    {
        "id": 159,
        "nombre": "Montale Fantastic Oud",
        "imagen": "montale-fantastic-oud",
        "casa": "Montale",
        "precio": "560.000 COP",
        "disponibilidad": "Solo original",
        "descripcion": "Perfume Montale Fantastic Oud de la casa Montale, conocido por su elegancia y sofisticación.",
        "aromas": "Amaderado"
    },
    {
        "id": 160,
        "nombre": "Montale Infinity",
        "imagen": "montale-infinity",
        "casa": "Montale",
        "precio": "590.000 COP",
        "disponibilidad": "Solo original",
        "descripcion": "Perfume Montale Infinity de la casa Montale, conocido por su elegancia y sofisticación.",
        "aromas": "Aroma variado"
    },
    {
        "id": 161,
        "nombre": "Montale Intense Café",
        "imagen": "montale-intense-café",
        "casa": "Montale",
        "precio": "560.000 COP",
        "disponibilidad": "Solo original",
        "descripcion": "Perfume Montale Intense Café de la casa Montale, conocido por su elegancia y sofisticación.",
        "aromas": "Aroma variado"
    },
    {
        "id": 162,
        "nombre": "Montale Intense Roses Musk",
        "imagen": "montale-intense-roses-musk",
        "casa": "Montale",
        "precio": "598.000 COP",
        "disponibilidad": "Solo original",
        "descripcion": "Perfume Montale Intense Roses Musk de la casa Montale, conocido por su elegancia y sofisticación.",
        "aromas": "Floral"
    },
    {
        "id": 163,
        "nombre": "Montale Roses Musk",
        "imagen": "montale-roses-musk",
        "casa": "Montale",
        "precio": "560.000 COP",
        "disponibilidad": "Solo original",
        "descripcion": "Perfume Montale Roses Musk de la casa Montale, conocido por su elegancia y sofisticación.",
        "aromas": "Floral"
    },
    {
        "id": 164,
        "nombre": "Montale Sensual Instinct",
        "imagen": "montale-sensual-instinct",
        "casa": "Montale",
        "precio": "590.000 COP",
        "disponibilidad": "Solo original",
        "descripcion": "Perfume Montale Sensual Instinct de la casa Montale, conocido por su elegancia y sofisticación.",
        "aromas": "Aroma variado"
    },
    {
        "id": 165,
        "nombre": "Montale Starry Nights",
        "imagen": "montale-starry-nights",
        "casa": "Montale",
        "precio": "560.000 COP",
        "disponibilidad": "Solo original",
        "descripcion": "Perfume Montale Starry Nights de la casa Montale, conocido por su elegancia y sofisticación.",
        "aromas": "Aroma variado"
    },
    {
        "id": 166,
        "nombre": "Moschino Funny",
        "imagen": "moschino-funny",
        "casa": "Moschino",
        "precio": "280.000 COP",
        "disponibilidad": "Solo original",
        "descripcion": "Perfume Moschino Funny de la casa Moschino, conocido por su elegancia y sofisticación.",
        "aromas": "Aroma variado"
    },
    {
        "id": 167,
        "nombre": "Moschino Toy 2",
        "imagen": "moschino-toy-2",
        "casa": "Moschino",
        "precio": "340.000 COP",
        "disponibilidad": "Solo original",
        "descripcion": "Perfume Moschino Toy 2 de la casa Moschino, conocido por su elegancia y sofisticación.",
        "aromas": "Aroma variado"
    },
    {
        "id": 168,
        "nombre": "Moschino Toy 2 Pearl",
        "imagen": "moschino-toy-2-pearl",
        "casa": "Moschino",
        "precio": "440.000 COP",
        "disponibilidad": "Solo original",
        "descripcion": "Perfume Moschino Toy 2 Pearl de la casa Moschino, conocido por su elegancia y sofisticación.",
        "aromas": "Aroma variado"
    },
    {
        "id": 169,
        "nombre": "Moschino Toy Boy",
        "imagen": "moschino-toy-boy",
        "casa": "Moschino",
        "precio": "389.000 COP",
        "disponibilidad": "Solo original",
        "descripcion": "Perfume Moschino Toy Boy de la casa Moschino, conocido por su elegancia y sofisticación.",
        "aromas": "Aroma variado"
    },
    {
        "id": 170,
        "nombre": "Mundus Burj Khalifa",
        "imagen": "mundus-burj-khalifa",
        "casa": "Mundus",
        "precio": "260.000 COP",
        "disponibilidad": "Solo original",
        "descripcion": "Perfume Mundus Burj Khalifa de la casa Mundus, conocido por su elegancia y sofisticación.",
        "aromas": "Aroma variado"
    },
    {
        "id": 171,
        "nombre": "Mundus Chichen Itza",
        "imagen": "mundus-chichen-itza",
        "casa": "Mundus",
        "precio": "260.000 COP",
        "disponibilidad": "Solo original",
        "descripcion": "Perfume Mundus Chichen Itza de la casa Mundus, conocido por su elegancia y sofisticación.",
        "aromas": "Aroma variado"
    },
    {
        "id": 172,
        "nombre": "Mundus Empire State",
        "imagen": "mundus-empire-state",
        "casa": "Mundus",
        "precio": "260.000 COP",
        "disponibilidad": "Solo original",
        "descripcion": "Perfume Mundus Empire State de la casa Mundus, conocido por su elegancia y sofisticación.",
        "aromas": "Aroma variado"
    },
    {
        "id": 173,
        "nombre": "Mundus Taj Mahal",
        "imagen": "mundus-taj-mahal",
        "casa": "Mundus",
        "precio": "260.000 COP",
        "disponibilidad": "Solo original",
        "descripcion": "Perfume Mundus Taj Mahal de la casa Mundus, conocido por su elegancia y sofisticación.",
        "aromas": "Aroma variado"
    },
    {
        "id": 174,
        "nombre": "Mundus Torre Eiffel",
        "imagen": "mundus-torre-eiffel",
        "casa": "Mundus",
        "precio": "260.000 COP",
        "disponibilidad": "Solo original",
        "descripcion": "Perfume Mundus Torre Eiffel de la casa Mundus, conocido por su elegancia y sofisticación.",
        "aromas": "Aroma variado"
    },
    {
        "id": 175,
        "nombre": "Orientica Amber Noir",
        "imagen": "orientica-amber-noir",
        "casa": "Orientica",
        "precio": "535.000 COP",
        "disponibilidad": "Solo original",
        "descripcion": "Perfume Orientica Amber Noir de la casa Orientica, conocido por su elegancia y sofisticación.",
        "aromas": "Aroma variado"
    },
    {
        "id": 176,
        "nombre": "Orientica Amber Rouge",
        "imagen": "orientica-amber-rouge",
        "casa": "Orientica",
        "precio": "499.000 COP",
        "disponibilidad": "Solo original",
        "descripcion": "Perfume Orientica Amber Rouge de la casa Orientica, conocido por su elegancia y sofisticación.",
        "aromas": "Aroma variado"
    },
    {
        "id": 177,
        "nombre": "Orientica Oud Saffron",
        "imagen": "orientica-oud-saffron",
        "casa": "Orientica",
        "precio": "499.000 COP",
        "disponibilidad": "Solo original",
        "descripcion": "Perfume Orientica Oud Saffron de la casa Orientica, conocido por su elegancia y sofisticación.",
        "aromas": "Amaderado"
    },
    {
        "id": 178,
        "nombre": "Orientica Royal Amber",
        "imagen": "orientica-royal-amber",
        "casa": "Orientica",
        "precio": "499.000 COP",
        "disponibilidad": "Solo original",
        "descripcion": "Perfume Orientica Royal Amber de la casa Orientica, conocido por su elegancia y sofisticación.",
        "aromas": "Aroma variado"
    },
    {
        "id": 179,
        "nombre": "Philipp Plein No Limits EDP",
        "imagen": "philipp-plein-no-limits-edp",
        "casa": "Philipp",
        "precio": "660.000 COP",
        "disponibilidad": "Solo original",
        "descripcion": "Perfume Philipp Plein No Limits EDP de la casa Philipp, conocido por su elegancia y sofisticación.",
        "aromas": "Aroma variado"
    },
    {
        "id": 180,
        "nombre": "Stallion 53",
        "imagen": "stallion-53",
        "casa": "Stallion",
        "precio": "270.000 COP",
        "disponibilidad": "Solo original",
        "descripcion": "Perfume Stallion 53 de la casa Stallion, conocido por su elegancia y sofisticación.",
        "aromas": "Aroma variado"
    },
    {
        "id": 181,
        "nombre": "Tester Stallion 53",
        "imagen": "tester-stallion-53",
        "casa": "Stallion",
        "precio": "230.000 COP",
        "disponibilidad": "Solo original",
        "descripcion": "Perfume Tester Stallion 53 de la casa Stallion, conocido por su elegancia y sofisticación.",
        "aromas": "Aroma variado"
    },
    {
        "id": 182,
        "nombre": "Carolina Herrera 212 Heroes Mujer",
        "imagen": "carolina-herrera-212-heroes-mujer",
        "casa": "Carolina Herrera",
        "precio": "118.000 COP",
        "disponibilidad": "Solo 1.1",
        "descripcion": "Perfume Carolina Herrera 212 Heroes Mujer de la casa Carolina Herrera, conocido por su elegancia y sofisticación.",
        "aromas": "Aroma variado"
    }
]